circleci/__init__.py
circleci/api.py
circleci/error.py
circleci/version.py
flashlexiot/__init__.py
flashlexiot/backend/__init__.py
flashlexiot/backend/callbacks.py
flashlexiot/backend/thread.py
flashlexiot/sdk/__init__.py
test/__init__.py
test/test_base.py
flashlexiot-0.9.16.dist-info/LICENSE
flashlexiot-0.9.16.dist-info/METADATA
flashlexiot-0.9.16.dist-info/WHEEL
flashlexiot-0.9.16.dist-info/top_level.txt
flashlexiot-0.9.16.dist-info/RECORD
