Metadata-Version: 2.1
Name: flashlexiot
Version: 0.9.16
Summary: Flashlex IOT for python makes it easy to make any python computer an IOT device.
Home-page: https://github.com/claytantor/flashlex-iot-python
Author: Clay Graham
Author-email: claytantor@flashlex.com
License: UNKNOWN
Platform: UNKNOWN
Classifier: Development Status :: 3 - Alpha
Classifier: Intended Audience :: Developers
Classifier: Topic :: Software Development :: Build Tools
Classifier: License :: OSI Approved :: MIT License
Classifier: Programming Language :: Python :: 3
Classifier: Programming Language :: Python :: 3.5
Classifier: Programming Language :: Python :: 3.6
Requires-Python: >=3.4
Requires-Dist: requests
